yucheng.py
yucheng-0.post1.dist-info/METADATA
yucheng-0.post1.dist-info/WHEEL
yucheng-0.post1.dist-info/top_level.txt
yucheng-0.post1.dist-info/RECORD
