Metadata-Version: 2.1
Name: yucheng
Version: 0-1
Summary: first issue
Home-page: http://disanda.github.io
Author: disanda
Author-email: disanda@foxmail.com
License: UNKNOWN
Platform: UNKNOWN
